{
	"version": 1495211523965,
	"shishens": [
		{
			"id": "tianxieguilv",
			"name": "天邪鬼绿",
			"queries": [
				"842694348458",
				"8945"
			],
			"clues": []
		},
		{
			"id": "tidengxiaoseng",
			"name": "提灯小僧",
			"queries": [
				"84336494267364",
				"8397"
			],
			"clues": []
		},
		{
			"id": "denglonggui",
			"name": "灯笼鬼",
			"queries": [
				"33645664484",
				"354"
			],
			"clues": []
		},
		{
			"id": "jiumingmao",
			"name": "九命猫",
			"queries": [
				"5486464626",
				"566"
			],
			"clues": []
		},
		{
			"id": "zhoushen",
			"name": "帚神",
			"queries": [
				"94687436",
				"97"
			],
			"clues": []
		},
		{
			"id": "jishenghun",
			"name": "寄生魂",
			"queries": [
				"5474364486",
				"574"
			],
			"clues": []
		},
		{
			"id": "daomuxiaogui",
			"name": "盗墓小鬼",
			"queries": [
				"326689426484",
				"3694"
			],
			"clues": []
		},
		{
			"id": "zuofutongzi",
			"name": "座敷童子",
			"queries": [
				"98638866494",
				"9389",
				"484486",
				"44",
				"5426",
				"5",
				"22438",
				"23",
				"9464986",
				"99"
			],
			"clues": [
				"鬼火",
				"角",
				"财富",
				"幸运"
			]
		},
		{
			"id": "tianxieguiqing",
			"name": "天邪鬼青",
			"queries": [
				"84269434847464",
				"8947",
				"74647438",
				"773",
				"336494364",
				"39"
			],
			"clues": [
				"青皮肤",
				"风筝"
			]
		},
		{
			"id": "tianxieguihuang",
			"name": "天邪鬼黄",
			"queries": [
				"842694348448264",
				"8944",
				"48",
				"4",
				"326926",
				"39"
			],
			"clues": [
				"鼓",
				"单眼"
			]
		},
		{
			"id": "tubi",
			"name": "涂壁",
			"queries": [
				"8824",
				"82",
				"744",
				"7",
				"7464824",
				"78",
				"74474264",
				"77"
			],
			"clues": [
				"石",
				"青苔",
				"石墙"
			]
		},
		{
			"id": "tongnv",
			"name": "童女",
			"queries": [
				"866468",
				"86",
				"2442264",
				"22",
				"9894",
				"99",
				"96868",
				"96"
			],
			"clues": [
				"翅膀",
				"羽衣",
				"幼女"
			]
		},
		{
			"id": "chishe",
			"name": "赤舌",
			"queries": [
				"244743",
				"27"
			],
			"clues": []
		},
		{
			"id": "yatiangou",
			"name": "鸦天狗",
			"queries": [
				"928426468",
				"984",
				"944326",
				"93",
				"2442264",
				"22",
				"642658",
				"65"
			],
			"clues": [
				"雉刀",
				"翅膀",
				"面具"
			]
		},
		{
			"id": "bingyong",
			"name": "兵俑",
			"queries": [
				"24649664",
				"29",
				"5426",
				"5",
				"5426542",
				"55",
				"744482",
				"74"
			],
			"clues": [
				"剑",
				"坚甲",
				"石化"
			]
		},
		{
			"id": "fenghuanghuo",
			"name": "凤凰火",
			"queries": [
				"336448264486",
				"344"
			],
			"clues": []
		},
		{
			"id": "tangzhisanyao",
			"name": "唐纸伞妖",
			"queries": [
				"8264944726926",
				"8979"
			],
			"clues": []
		},
		{
			"id": "tianxieguichi",
			"name": "天邪鬼赤",
			"queries": [
				"8426943484244",
				"8942",
				"4664484",
				"44",
				"7247448",
				"774"
			],
			"clues": [
				"红鬼",
				"拍屁股"
			]
		},
		{
			"id": "yunv",
			"name": "雨女",
			"queries": [
				"9868",
				"96",
				"534948",
				"59",
				"98",
				"9",
				"726",
				"7"
			],
			"clues": [
				"泪珠",
				"雨",
				"伞"
			]
		},
		{
			"id": "qingwaciqi",
			"name": "青蛙瓷器",
			"queries": [
				"7464922474",
				"7927",
				"378664",
				"38",
				"24",
				"2",
				"2487426",
				"27"
			],
			"clues": [
				"二筒",
				"瓷",
				"出千"
			]
		},
		{
			"id": "heibao",
			"name": "黑豹",
			"queries": [
				"434226",
				"42"
			],
			"clues": []
		},
		{
			"id": "guanhu",
			"name": "管狐",
			"queries": [
				"482648",
				"44"
			],
			"clues": []
		},
		{
			"id": "shifagui",
			"name": "食发鬼",
			"queries": [
				"74432484",
				"734"
			],
			"clues": []
		},
		{
			"id": "hudiejing",
			"name": "蝴蝶精",
			"queries": [
				"483435464",
				"435",
				"746848",
				"74",
				"94269265464",
				"995",
				"5324",
				"52"
			],
			"clues": [
				"手鼓",
				"小妖精",
				"可爱"
			]
		},
		{
			"id": "sanweihu",
			"name": "三尾狐",
			"queries": [
				"72693448",
				"794",
				"9464482748",
				"947",
				"466473",
				"47",
				"94264926926",
				"999",
				"4664934",
				"49"
			],
			"clues": [
				"樱花树",
				"红色",
				"杖妖艳",
				"红尾"
			]
		},
		{
			"id": "wugushi",
			"name": "巫蛊师",
			"queries": [
				"9848744",
				"947"
			],
			"clues": []
		},
		{
			"id": "liyujing",
			"name": "鲤鱼精",
			"queries": [
				"54985464",
				"595",
				"7484244",
				"72",
				"7484726",
				"77",
				"93422",
				"92"
			],
			"clues": [
				"水池",
				"水泡",
				"尾巴"
			]
		},
		{
			"id": "hetong",
			"name": "河童",
			"queries": [
				"438664",
				"48",
				"7484748",
				"77",
				"43548",
				"45",
				"4393",
				"49"
			],
			"clues": [
				"水球",
				"河流",
				"荷叶"
			]
		},
		{
			"id": "tiaotiaoquan",
			"name": "跳跳犬",
			"queries": [
				"842684267826",
				"887"
			],
			"clues": []
		},
		{
			"id": "yaohu",
			"name": "妖狐",
			"queries": [
				"92648",
				"94",
				"9447426",
				"97",
				"74874364",
				"77",
				"642658",
				"65"
			],
			"clues": [
				"纸扇",
				"书生",
				"面具"
			]
		},
		{
			"id": "shantong",
			"name": "山童",
			"queries": [
				"74268664",
				"78",
				"326926",
				"39",
				"7442484",
				"72",
				"482454",
				"45"
			],
			"clues": [
				"单眼",
				"石锤",
				"怪力"
			]
		},
		{
			"id": "yinghuayao",
			"name": "樱花妖",
			"queries": [
				"9464482926",
				"949"
			],
			"clues": []
		},
		{
			"id": "xuenv",
			"name": "雪女",
			"queries": [
				"98368",
				"96"
			],
			"clues": []
		},
		{
			"id": "taohuayao",
			"name": "桃花妖",
			"queries": [
				"826482926",
				"849",
				"482",
				"4",
				"98",
				"9"
			],
			"clues": [
				"花",
				"舞"
			]
		},
		{
			"id": "tieshu",
			"name": "铁鼠",
			"queries": [
				"843748",
				"87"
			],
			"clues": []
		},
		{
			"id": "shantu",
			"name": "山兔",
			"queries": [
				"742688",
				"78"
			],
			"clues": []
		},
		{
			"id": "mengpo",
			"name": "孟婆",
			"queries": [
				"636476",
				"67",
				"8264926",
				"89",
				"746",
				"7",
				"9292",
				"99"
			],
			"clues": [
				"汤碗",
				"琴",
				"牙牙"
			]
		},
		{
			"id": "egui",
			"name": "饿鬼",
			"queries": [
				"3484",
				"34"
			],
			"clues": []
		},
		{
			"id": "choushizhinv",
			"name": "丑时之女",
			"queries": [
				"246874494468",
				"2796",
				"326226736",
				"327",
				"94689484",
				"99"
			],
			"clues": [
				"稻草人",
				"咒锥"
			]
		},
		{
			"id": "kuileishi",
			"name": "傀儡师",
			"queries": [
				"584534744",
				"557",
				"73668",
				"76",
				"2269664",
				"29"
			],
			"clues": [
				"人偶",
				"操纵"
			]
		},
		{
			"id": "jue",
			"name": "觉",
			"queries": [
				"583",
				"5"
			],
			"clues": []
		},
		{
			"id": "limao",
			"name": "狸猫",
			"queries": [
				"54626",
				"56"
			],
			"clues": []
		},
		{
			"id": "quanshen",
			"name": "犬神",
			"queries": [
				"78267436",
				"77",
				"5426783",
				"57",
				"98",
				"9",
				"746848",
				"74"
			],
			"clues": [
				"剑雀",
				"屋",
				"守护"
			]
		},
		{
			"id": "jiutuntongzi",
			"name": "酒吞童子",
			"queries": [
				"548886866494",
				"5889"
			],
			"clues": []
		},
		{
			"id": "tiaotiaogege",
			"name": "跳跳哥哥",
			"queries": [
				"842684264343",
				"8844",
				"52948",
				"59",
				"4826224",
				"42"
			],
			"clues": [
				"蜡烛",
				"棺材"
			]
		},
		{
			"id": "gunv",
			"name": "骨女",
			"queries": [
				"4868",
				"46",
				"58568",
				"55",
				"98266426",
				"96",
				"5426",
				"5"
			],
			"clues": [
				"骷髅",
				"怨念",
				"剑"
			]
		},
		{
			"id": "wushizhiling",
			"name": "武士之灵",
			"queries": [
				"987449445464",
				"9795"
			],
			"clues": []
		},
		{
			"id": "duyanxiaoseng",
			"name": "独眼小僧",
			"queries": [
				"3892694267364",
				"3997",
				"326926",
				"39",
				"7447872",
				"777",
				"54642645464",
				"545"
			],
			"clues": [
				"单眼",
				"石菩萨",
				"金刚经"
			]
		},
		{
			"id": "guinvhongye",
			"name": "鬼女红叶",
			"queries": [
				"48468466493",
				"4649"
			],
			"clues": []
		},
		{
			"id": "haifangzhu",
			"name": "海坊主",
			"queries": [
				"4243264948",
				"439",
				"9838",
				"93",
				"424",
				"4",
				"4898",
				"49",
				"94264",
				"9"
			],
			"clues": [
				"渔夫",
				"海",
				"胡须",
				"杖"
			]
		},
		{
			"id": "tongnan",
			"name": "童男",
			"queries": [
				"8664626",
				"86",
				"2442264",
				"22",
				"9894",
				"99",
				"942654",
				"95"
			],
			"clues": [
				"翅膀",
				"雨衣",
				"献祭"
			]
		},
		{
			"id": "tiaotiaomeimei",
			"name": "跳跳妹妹",
			"queries": [
				"84268426634634",
				"8866"
			],
			"clues": []
		},
		{
			"id": "shouwu",
			"name": "首无",
			"queries": [
				"746898",
				"79"
			],
			"clues": []
		},
		{
			"id": "shimengmo",
			"name": "食梦貘",
			"queries": [
				"744636466",
				"766",
				"54643264",
				"53",
				"36364",
				"36"
			],
			"clues": [
				"铃铛",
				"噩梦"
			]
		},
		{
			"id": "datiangou",
			"name": "大天狗",
			"queries": [
				"328426468",
				"384",
				"322442264",
				"322",
				"3364",
				"3",
				"7426",
				"7"
			],
			"clues": [
				"大翅膀",
				"风",
				"扇"
			]
		},
		{
			"id": "panguan",
			"name": "判官",
			"queries": [
				"7264826",
				"74"
			],
			"clues": []
		},
		{
			"id": "guishihei",
			"name": "鬼使黑",
			"queries": [
				"484744434",
				"474",
				"4345426",
				"45",
				"3826326",
				"33"
			],
			"clues": [
				"黑镰",
				"短刀"
			]
		},
		{
			"id": "guishibai",
			"name": "鬼使白",
			"queries": [
				"484744224",
				"472",
				"6464543",
				"65",
				"224",
				"2",
				"3866464",
				"36"
			],
			"clues": [
				"冥界",
				"白",
				"夺命"
			]
		},
		{
			"id": "fengxiaoqilin",
			"name": "风小麒麟",
			"queries": [
				"3364942674546",
				"3975"
			],
			"clues": []
		},
		{
			"id": "huoxiaoqilin",
			"name": "火小麒麟",
			"queries": [
				"486942674546",
				"4975"
			],
			"clues": []
		},
		{
			"id": "heifenghuang",
			"name": "黑凤凰",
			"queries": [
				"434336448264",
				"434"
			],
			"clues": []
		},
		{
			"id": "huangchuanzhizhu",
			"name": "荒川之主",
			"queries": [
				"4826424826944948",
				"4299"
			],
			"clues": []
		},
		{
			"id": "tiaotiaodidi",
			"name": "跳跳弟弟",
			"queries": [
				"842684263434",
				"8833"
			],
			"clues": []
		},
		{
			"id": "yaodaoji",
			"name": "妖刀姬",
			"queries": [
				"92632654",
				"935"
			],
			"clues": []
		},
		{
			"id": "fengweidamo",
			"name": "奉为达摩",
			"queries": [
				"33649343266",
				"3936"
			],
			"clues": []
		},
		{
			"id": "yuhangdamo",
			"name": "御行达摩",
			"queries": [
				"9842643266",
				"9436"
			],
			"clues": []
		},
		{
			"id": "zhaofudamo",
			"name": "招福达摩",
			"queries": [
				"9426383266",
				"9336"
			],
			"clues": []
		},
		{
			"id": "dajidamo",
			"name": "大吉达摩",
			"queries": [
				"32543266",
				"3536"
			],
			"clues": []
		},
		{
			"id": "baitongzi",
			"name": "白童子",
			"queries": [
				"224866494",
				"289"
			],
			"clues": []
		},
		{
			"id": "heitongzi",
			"name": "黑童子",
			"queries": [
				"434866494",
				"489"
			],
			"clues": []
		},
		{
			"id": "huibishou",
			"name": "惠比寿",
			"queries": [
				"484247468",
				"427"
			],
			"clues": []
		},
		{
			"id": "yanyanluo",
			"name": "烟烟罗",
			"queries": [
				"926926586",
				"995"
			],
			"clues": []
		},
		{
			"id": "lianyou",
			"name": "镰鼬",
			"queries": [
				"5426968",
				"59",
				"248494",
				"29",
				"346422",
				"32",
				"5426",
				"5"
			],
			"clues": [
				"锤子",
				"钉耙",
				"剑"
			]
		},
		{
			"id": "yingcao",
			"name": "莹草",
			"queries": [
				"9464226",
				"92",
				"7846649464",
				"749",
				"9445426",
				"95"
			],
			"clues": [
				"蒲公英",
				"治疗"
			]
		},
		{
			"id": "baqidashe",
			"name": "八歧大蛇",
			"queries": [
				"227432743",
				"2737"
			],
			"clues": []
		},
		{
			"id": "xixieji",
			"name": "吸血姬",
			"queries": [
				"9494354",
				"995",
				"943",
				"9",
				"242638",
				"23"
			],
			"clues": [
				"血",
				"蝙蝠"
			]
		},
		{
			"id": "jiaotu",
			"name": "椒图",
			"queries": [
				"542688",
				"58",
				"23453",
				"25",
				"742694",
				"79",
				"93422",
				"92"
			],
			"clues": [
				"贝壳",
				"扇子",
				"尾巴"
			]
		},
		{
			"id": "yanmo",
			"name": "阎魔",
			"queries": [
				"92666",
				"96",
				"986",
				"9",
				"4846426",
				"46",
				"6464543",
				"65"
			],
			"clues": [
				"云",
				"鬼面",
				"冥界"
			]
		},
		{
			"id": "yaoqinshi",
			"name": "妖琴师",
			"queries": [
				"926746744",
				"977"
			],
			"clues": []
		},
		{
			"id": "bailang",
			"name": "白狼",
			"queries": [
				"2245264",
				"25"
			],
			"clues": []
		},
		{
			"id": "cimutongzi",
			"name": "茨木童子",
			"queries": [
				"2468866494",
				"2689"
			],
			"clues": []
		},
		{
			"id": "qingji",
			"name": "清姬",
			"queries": [
				"746454",
				"75"
			],
			"clues": []
		},
		{
			"id": "liangmianfo",
			"name": "两面佛",
			"queries": [
				"54264642636",
				"563"
			],
			"clues": []
		},
		{
			"id": "erkounv",
			"name": "二口女",
			"queries": [
				"3756868",
				"356"
			],
			"clues": []
		},
		{
			"id": "qinghangdeng",
			"name": "青行灯",
			"queries": [
				"746442643364",
				"743"
			],
			"clues": []
		}
	],
	"dungeons": [
		{
			"name": "第一章 天邪鬼绿1",
			"sushi": 3,
			"rounds": [
				{
					"enemies": {
						"tianxieguilv": 1,
						"tidengxiaoseng": 2
					}
				}
			],
			"money": 0,
			"exp": 0
		},
		{
			"name": "第一章 天邪鬼绿2",
			"sushi": 3,
			"rounds": [
				{
					"enemies": {
						"tianxieguilv": 1,
						"denglonggui": 2
					}
				}
			],
			"money": 0,
			"exp": 0
		},
		{
			"name": "第一章 提灯小僧1",
			"sushi": 3,
			"rounds": [
				{
					"enemies": {
						"tianxieguilv": 2,
						"tidengxiaoseng": 1
					}
				}
			],
			"money": 0,
			"exp": 0
		},
		{
			"name": "第一章 提灯小僧2",
			"sushi": 3,
			"rounds": [
				{
					"enemies": {
						"denglonggui": 2,
						"tidengxiaoseng": 1
					}
				}
			],
			"money": 0,
			"exp": 0
		},
		{
			"name": "第一章 首领：九命猫",
			"sushi": 3,
			"rounds": [
				{
					"enemies": {
						"jiumingmao": 3
					}
				}
			],
			"money": 0,
			"exp": 0
		},
		{
			"name": "第二章 帚神",
			"sushi": 3,
			"rounds": [
				{
					"enemies": {
						"zhoushen": 1,
						"jishenghun": 1,
						"daomuxiaogui": 1
					}
				}
			],
			"money": 0,
			"exp": 0
		},
		{
			"name": "第二章 盗墓小鬼1",
			"sushi": 3,
			"rounds": [
				{
					"enemies": {
						"jishenghun": 2,
						"daomuxiaogui": 1
					}
				}
			],
			"money": 0,
			"exp": 0
		},
		{
			"name": "第二章 盗墓小鬼2",
			"sushi": 3,
			"rounds": [
				{
					"enemies": {
						"denglonggui": 2,
						"daomuxiaogui": 1
					}
				}
			],
			"money": 0,
			"exp": 0
		},
		{
			"name": "第二章 寄生魂1",
			"sushi": 3,
			"rounds": [
				{
					"enemies": {
						"denglonggui": 2,
						"jishenghun": 1
					}
				}
			],
			"money": 0,
			"exp": 0
		},
		{
			"name": "第二章 寄生魂2",
			"sushi": 3,
			"rounds": [
				{
					"enemies": {
						"daomuxiaogui": 2,
						"jishenghun": 1
					}
				}
			],
			"money": 0,
			"exp": 0
		},
		{
			"name": "第二章 首领：座敷童子",
			"sushi": 3,
			"rounds": [
				{
					"enemies": {
						"tianxieguilv": 2,
						"tianxieguiqing": 1,
						"zuofutongzi": 1
					}
				}
			],
			"money": 0,
			"exp": 0
		},
		{
			"name": "第三章 天邪鬼黄1",
			"sushi": 3,
			"rounds": [
				{
					"enemies": {
						"tianxieguihuang": 1,
						"zhoushen": 2,
						"tubi": 1
					}
				}
			],
			"money": 0,
			"exp": 0
		},
		{
			"name": "第三章 天邪鬼黄2",
			"sushi": 3,
			"rounds": [
				{
					"enemies": {
						"tongnv": 3,
						"tianxieguihuang": 1
					}
				}
			],
			"money": 0,
			"exp": 0
		},
		{
			"name": "第三章 赤舌1",
			"sushi": 3,
			"rounds": [
				{
					"enemies": {
						"chishe": 1,
						"tidengxiaoseng": 1,
						"denglonggui": 2
					}
				},
				{
					"enemies": {
						"yatiangou": 1
					}
				}
			],
			"money": 0,
			"exp": 0
		},
		{
			"name": "第三章 赤舌2",
			"sushi": 3,
			"rounds": [
				{
					"enemies": {
						"chishe": 1,
						"tianxieguihuang": 1,
						"tongnv": 2
					}
				},
				{
					"enemies": {
						"yatiangou": 1
					}
				}
			],
			"money": 0,
			"exp": 0
		},
		{
			"name": "第三章 兵俑1",
			"sushi": 3,
			"rounds": [
				{
					"enemies": {
						"bingyong": 1,
						"tidengxiaoseng": 1,
						"tongnv": 2
					}
				}
			],
			"money": 0,
			"exp": 0
		},
		{
			"name": "第三章 兵俑2",
			"sushi": 3,
			"rounds": [
				{
					"enemies": {
						"bingyong": 1,
						"tidengxiaoseng": 1,
						"denglonggui": 2
					}
				}
			],
			"money": 0,
			"exp": 0
		},
		{
			"name": "第三章 首领：凤凰火",
			"sushi": 3,
			"rounds": [
				{
					"enemies": {
						"fenghuanghuo": 1,
						"jishenghun": 3
					}
				}
			],
			"money": 0,
			"exp": 0
		},
		{
			"name": "第四章 帚神1",
			"sushi": 3,
			"rounds": [
				{
					"enemies": {
						"zhoushen": 1,
						"tubi": 2
					}
				}
			],
			"money": 0,
			"exp": 0
		},
		{
			"name": "第四章 帚神2",
			"sushi": 3,
			"rounds": [
				{
					"enemies": {
						"zhoushen": 1,
						"tangzhisanyao": 3
					}
				}
			],
			"money": 0,
			"exp": 0
		},
		{
			"name": "第四章 唐纸伞妖1",
			"sushi": 3,
			"rounds": [
				{
					"enemies": {
						"tangzhisanyao": 1,
						"tianxieguichi": 3
					}
				}
			],
			"money": 0,
			"exp": 0
		},
		{
			"name": "第四章 唐纸伞妖2",
			"sushi": 3,
			"rounds": [
				{
					"enemies": {
						"tangzhisanyao": 1,
						"tianxieguichi": 1,
						"tubi": 2
					}
				}
			],
			"money": 0,
			"exp": 0
		},
		{
			"name": "第四章 天邪鬼赤1",
			"sushi": 3,
			"rounds": [
				{
					"enemies": {
						"tianxieguichi": 1,
						"tangzhisanyao": 1,
						"tubi": 2
					}
				}
			],
			"money": 0,
			"exp": 0
		},
		{
			"name": "第四章 天邪鬼赤2",
			"sushi": 3,
			"rounds": [
				{
					"enemies": {
						"tianxieguichi": 1,
						"tangzhisanyao": 2
					}
				}
			],
			"money": 0,
			"exp": 0
		},
		{
			"name": "第四章 首领：雨女",
			"sushi": 3,
			"rounds": [
				{
					"enemies": {
						"yunv": 1,
						"qingwaciqi": 1,
						"zhoushen": 2
					}
				}
			],
			"money": 0,
			"exp": 0
		},
		{
			"name": "第五章 涂壁1",
			"sushi": 3,
			"rounds": [
				{
					"enemies": {
						"tubi": 1,
						"heibao": 1,
						"tianxieguichi": 2
					}
				}
			],
			"money": 0,
			"exp": 0
		},
		{
			"name": "第五章 涂壁2",
			"sushi": 3,
			"rounds": [
				{
					"enemies": {
						"tubi": 1,
						"tianxieguichi": 3
					}
				}
			],
			"money": 0,
			"exp": 0
		},
		{
			"name": "第五章 帚神1",
			"sushi": 3,
			"rounds": [
				{
					"enemies": {
						"zhoushen": 1,
						"tianxieguichi": 1,
						"tubi": 2
					}
				}
			],
			"money": 0,
			"exp": 0
		},
		{
			"name": "第五章 帚神2",
			"sushi": 3,
			"rounds": [
				{
					"enemies": {
						"zhoushen": 1,
						"tianxieguichi": 1,
						"tianxieguihuang": 2
					}
				}
			],
			"money": 0,
			"exp": 0
		},
		{
			"name": "第五章 管狐1",
			"sushi": 3,
			"rounds": [
				{
					"enemies": {
						"guanhu": 2,
						"tianxieguihuang": 2
					}
				},
				{
					"enemies": {
						"jishenghun": 1
					}
				}
			],
			"money": 0,
			"exp": 0
		},
		{
			"name": "第五章 管狐2",
			"sushi": 3,
			"rounds": [
				{
					"enemies": {
						"guanhu": 1,
						"tianxieguilv": 3
					}
				},
				{
					"enemies": {
						"jishenghun": 1
					}
				}
			],
			"money": 0,
			"exp": 0
		},
		{
			"name": "第五章 首领：食发鬼",
			"sushi": 3,
			"rounds": [
				{
					"enemies": {
						"shifagui": 1,
						"denglonggui": 1,
						"tianxieguiqing": 2
					}
				}
			],
			"money": 0,
			"exp": 0
		},
		{
			"name": "第六章 灯笼鬼",
			"sushi": 3,
			"rounds": [
				{
					"enemies": {
						"denglonggui": 1,
						"zhoushen": 3
					}
				}
			],
			"money": 0,
			"exp": 0
		},
		{
			"name": "第六章 天邪鬼青",
			"sushi": 3,
			"rounds": [
				{
					"enemies": {
						"tianxieguiqing": 1,
						"tianxieguilv": 3
					}
				}
			],
			"money": 0,
			"exp": 0
		},
		{
			"name": "第六章 蝴蝶精",
			"sushi": 3,
			"rounds": [
				{
					"enemies": {
						"hudiejing": 1,
						"tubi": 1,
						"tianxieguichi": 2
					}
				},
				{
					"enemies": {
						"sanweihu": 1
					}
				}
			],
			"money": 0,
			"exp": 0
		},
		{
			"name": "第六章 首领：巫蛊师",
			"sushi": 3,
			"rounds": [
				{
					"enemies": {
						"wugushi": 1,
						"tianxieguilv": 3
					}
				}
			],
			"money": 0,
			"exp": 0
		},
		{
			"name": "第七章 鲤鱼精1",
			"sushi": 3,
			"rounds": [
				{
					"enemies": {
						"liyujing": 3,
						"zhoushen": 1
					}
				}
			],
			"money": 0,
			"exp": 0
		},
		{
			"name": "第七章 鲤鱼精2",
			"sushi": 3,
			"rounds": [
				{
					"enemies": {
						"liyujing": 1,
						"zhoushen": 3
					}
				}
			],
			"money": 0,
			"exp": 0
		},
		{
			"name": "第七章 河童1",
			"sushi": 3,
			"rounds": [
				{
					"enemies": {
						"hetong": 1,
						"liyujing": 1,
						"tubi": 2
					}
				}
			],
			"money": 0,
			"exp": 0
		},
		{
			"name": "第七章 河童2",
			"sushi": 3,
			"rounds": [
				{
					"enemies": {
						"hetong": 1,
						"denglonggui": 1,
						"tiaotiaoquan": 2
					}
				}
			],
			"money": 0,
			"exp": 0
		},
		{
			"name": "第七章 提灯小僧1",
			"sushi": 3,
			"rounds": [
				{
					"enemies": {
						"tidengxiaoseng": 1,
						"tiaotiaoquan": 3
					}
				},
				{
					"enemies": {
						"guanhu": 1
					}
				}
			],
			"money": 0,
			"exp": 0
		},
		{
			"name": "第七章 提灯小僧2",
			"sushi": 3,
			"rounds": [
				{
					"enemies": {
						"tidengxiaoseng": 1,
						"tiaotiaoquan": 3
					}
				},
				{
					"enemies": {
						"guanhu": 1
					}
				}
			],
			"money": 0,
			"exp": 0
		},
		{
			"name": "第七章 提灯小僧3",
			"sushi": 3,
			"rounds": [
				{
					"enemies": {
						"tidengxiaoseng": 1,
						"tiaotiaoquan": 1,
						"liyujing": 2
					}
				}
			],
			"money": 0,
			"exp": 0
		},
		{
			"name": "第七章 首领：妖狐",
			"sushi": 3,
			"rounds": [
				{
					"enemies": {
						"yaohu": 1,
						"tubi": 1,
						"zuofutongzi": 2
					}
				},
				{
					"enemies": {
						"yaohu": 1,
						"jishenghun": 1,
						"tianxieguichi": 2
					}
				}
			],
			"money": 0,
			"exp": 0
		},
		{
			"name": "第八章 唐纸伞妖1",
			"sushi": 3,
			"rounds": [
				{
					"enemies": {
						"tangzhisanyao": 1,
						"zhoushen": 3
					}
				}
			],
			"money": 0,
			"exp": 0
		},
		{
			"name": "第八章 唐纸伞妖2",
			"sushi": 3,
			"rounds": [
				{
					"enemies": {
						"tangzhisanyao": 1,
						"shantong": 1,
						"zhoushen": 2
					}
				}
			],
			"money": 0,
			"exp": 0
		},
		{
			"name": "第八章 樱花妖1",
			"sushi": 3,
			"rounds": [
				{
					"enemies": {
						"yinghuayao": 1,
						"zhoushen": 1,
						"tubi": 2
					}
				},
				{
					"enemies": {
						"xuenv": 1
					}
				}
			],
			"money": 0,
			"exp": 0
		},
		{
			"name": "第八章 樱花妖2",
			"sushi": 3,
			"rounds": [
				{
					"enemies": {
						"yinghuayao": 1,
						"tubi": 3
					}
				},
				{
					"enemies": {
						"xuenv": 1
					}
				}
			],
			"money": 0,
			"exp": 0
		},
		{
			"name": "第八章 天邪鬼绿",
			"sushi": 3,
			"rounds": [
				{
					"enemies": {
						"tianxieguilv": 1,
						"tianxieguiqing": 1,
						"tianxieguihuang": 2
					}
				}
			],
			"money": 0,
			"exp": 0
		},
		{
			"name": "第八章 首领：桃花妖",
			"sushi": 3,
			"rounds": [
				{
					"enemies": {
						"yinghuayao": 1,
						"tianxieguiqing": 1,
						"tidengxiaoseng": 2
					}
				},
				{
					"enemies": {
						"taohuayao": 1,
						"zhoushen": 1,
						"hudiejing": 2
					}
				}
			],
			"money": 0,
			"exp": 0
		},
		{
			"name": "第九章 提灯小僧1",
			"sushi": 3,
			"rounds": [
				{
					"enemies": {
						"tidengxiaoseng": 1,
						"denglonggui": 3
					}
				}
			],
			"money": 0,
			"exp": 0
		},
		{
			"name": "第九章 提灯小僧2",
			"sushi": 3,
			"rounds": [
				{
					"enemies": {
						"tidengxiaoseng": 1,
						"denglonggui": 1,
						"tieshu": 2
					}
				}
			],
			"money": 0,
			"exp": 0
		},
		{
			"name": "第九章 铁鼠1",
			"sushi": 3,
			"rounds": [
				{
					"enemies": {
						"tieshu": 1,
						"zhoushen": 3
					}
				}
			],
			"money": 0,
			"exp": 0
		},
		{
			"name": "第九章 铁鼠2",
			"sushi": 3,
			"rounds": [
				{
					"enemies": {
						"tieshu": 2,
						"zhoushen": 2
					}
				}
			],
			"money": 0,
			"exp": 0
		},
		{
			"name": "第九章 山兔1",
			"sushi": 3,
			"rounds": [
				{
					"enemies": {
						"shantu": 4
					}
				},
				{
					"enemies": {
						"yatiangou": 1
					}
				}
			],
			"money": 0,
			"exp": 0
		},
		{
			"name": "第九章 山兔2",
			"sushi": 3,
			"rounds": [
				{
					"enemies": {
						"shantu": 3,
						"tieshu": 1
					}
				},
				{
					"enemies": {
						"yatiangou": 1
					}
				}
			],
			"money": 0,
			"exp": 0
		},
		{
			"name": "第九章 首领：孟婆",
			"sushi": 3,
			"rounds": [
				{
					"enemies": {
						"mengpo": 1,
						"egui": 3
					}
				},
				{
					"enemies": {
						"mengpo": 1,
						"denglonggui": 1,
						"yatiangou": 2
					}
				}
			],
			"money": 0,
			"exp": 0
		},
		{
			"name": "第十章 丑时之女",
			"sushi": 3,
			"rounds": [
				{
					"enemies": {
						"choushizhinv": 1,
						"kuileishi": 1,
						"tianxieguiqing": 2
					}
				}
			],
			"money": 0,
			"exp": 0
		},
		{
			"name": "第十章 傀儡师1",
			"sushi": 3,
			"rounds": [
				{
					"enemies": {
						"kuileishi": 1,
						"jue": 1,
						"limao": 2
					}
				}
			],
			"money": 0,
			"exp": 0
		},
		{
			"name": "第十章 傀儡师2",
			"sushi": 3,
			"rounds": [
				{
					"enemies": {
						"kuileishi": 1,
						"jue": 1,
						"zuofutongzi": 2
					}
				},
				{
					"enemies": {
						"quanshen": 1
					}
				}
			],
			"money": 0,
			"exp": 0
		},
		{
			"name": "第十章 觉1",
			"sushi": 3,
			"rounds": [
				{
					"enemies": {
						"jue": 1,
						"limao": 3
					}
				}
			],
			"money": 0,
			"exp": 0
		},
		{
			"name": "第十章 觉2",
			"sushi": 3,
			"rounds": [
				{
					"enemies": {
						"jue": 1,
						"chishe": 1,
						"zuofutongzi": 2
					}
				},
				{
					"enemies": {
						"quanshen": 1
					}
				}
			],
			"money": 0,
			"exp": 0
		},
		{
			"name": "第十章 首领：酒吞童子",
			"sushi": 3,
			"rounds": [
				{
					"enemies": {
						"jiutuntongzi": 1,
						"tiaotiaogege": 1,
						"shifagui": 2
					}
				},
				{
					"enemies": {
						"jiutuntongzi": 1,
						"bingyong": 1,
						"gunv": 2
					}
				}
			],
			"money": 0,
			"exp": 0
		},
		{
			"name": "第十一章 武士之灵1",
			"sushi": 3,
			"rounds": [
				{
					"enemies": {
						"wushizhiling": 1,
						"jishenghun": 3
					}
				}
			],
			"money": 0,
			"exp": 0
		},
		{
			"name": "第十一章 武士之灵2",
			"sushi": 3,
			"rounds": [
				{
					"enemies": {
						"wushizhiling": 1,
						"duyanxiaoseng": 3
					}
				}
			],
			"money": 0,
			"exp": 0
		},
		{
			"name": "第十一章 独眼小僧1",
			"sushi": 3,
			"rounds": [
				{
					"enemies": {
						"duyanxiaoseng": 1,
						"tubi": 1,
						"tianxieguichi": 2
					}
				},
				{
					"enemies": {
						"duyanxiaoseng": 1
					}
				}
			],
			"money": 0,
			"exp": 0
		},
		{
			"name": "第十一章 独眼小僧2",
			"sushi": 3,
			"rounds": [
				{
					"enemies": {
						"duyanxiaoseng": 1,
						"guanhu": 1,
						"tianxieguichi": 2
					}
				},
				{
					"enemies": {
						"duyanxiaoseng": 1
					}
				}
			],
			"money": 0,
			"exp": 0
		},
		{
			"name": "第十一章 饿鬼1",
			"sushi": 3,
			"rounds": [
				{
					"enemies": {
						"egui": 1,
						"tubi": 1,
						"guanhu": 2
					}
				}
			],
			"money": 0,
			"exp": 0
		},
		{
			"name": "第十一章 饿鬼2",
			"sushi": 3,
			"rounds": [
				{
					"enemies": {
						"egui": 3,
						"guanhu": 1
					}
				}
			],
			"money": 0,
			"exp": 0
		},
		{
			"name": "第十一章 首领：鬼女红叶",
			"sushi": 3,
			"rounds": [
				{
					"enemies": {
						"guinvhongye": 1,
						"tongnv": 1,
						"tianxieguiqing": 2
					}
				},
				{
					"enemies": {
						"guinvhongye": 1,
						"gunv": 1,
						"jue": 2
					}
				}
			],
			"money": 0,
			"exp": 0
		},
		{
			"name": "第十二章 海坊主1",
			"sushi": 3,
			"rounds": [
				{
					"enemies": {
						"haifangzhu": 1,
						"zhoushen": 1,
						"tubi": 2
					}
				}
			],
			"money": 0,
			"exp": 0
		},
		{
			"name": "第十二章 海坊主2",
			"sushi": 3,
			"rounds": [
				{
					"enemies": {
						"haifangzhu": 1,
						"tubi": 1,
						"yatiangou": 2
					}
				}
			],
			"money": 0,
			"exp": 0
		},
		{
			"name": "第十二章 童男1",
			"sushi": 3,
			"rounds": [
				{
					"enemies": {
						"tongnan": 1,
						"tianxieguihuang": 1,
						"yatiangou": 2
					}
				}
			],
			"money": 0,
			"exp": 0
		},
		{
			"name": "第十二章 童男2",
			"sushi": 3,
			"rounds": [
				{
					"enemies": {
						"tongnan": 1,
						"tongnv": 1,
						"yatiangou": 2
					}
				}
			],
			"money": 0,
			"exp": 0
		},
		{
			"name": "第十二章 童女1",
			"sushi": 3,
			"rounds": [
				{
					"enemies": {
						"tongnv": 1,
						"daomuxiaogui": 1,
						"tidengxiaoseng": 2
					}
				},
				{
					"enemies": {
						"xuenv": 1
					}
				}
			],
			"money": 0,
			"exp": 0
		},
		{
			"name": "第十二章 童女2",
			"sushi": 3,
			"rounds": [
				{
					"enemies": {
						"tongnv": 3,
						"daomuxiaogui": 1
					}
				},
				{
					"enemies": {
						"xuenv": 1
					}
				}
			],
			"money": 0,
			"exp": 0
		},
		{
			"name": "第十二章 首领：雪女",
			"sushi": 3,
			"rounds": [
				{
					"enemies": {
						"xuenv": 1,
						"jishenghun": 1,
						"wushizhiling": 2
					}
				},
				{
					"enemies": {
						"xuenv": 1,
						"tiaotiaomeimei": 1,
						"tiaotiaogege": 2
					}
				}
			],
			"money": 0,
			"exp": 0
		},
		{
			"name": "第十三章 饿鬼1",
			"sushi": 3,
			"rounds": [
				{
					"enemies": {
						"egui": 1,
						"tianxieguichi": 3
					}
				}
			],
			"money": 0,
			"exp": 0
		},
		{
			"name": "第十三章 饿鬼2",
			"sushi": 3,
			"rounds": [
				{
					"enemies": {
						"egui": 1,
						"tianxieguichi": 3
					}
				}
			],
			"money": 0,
			"exp": 0
		},
		{
			"name": "第十三章 饿鬼3",
			"sushi": 3,
			"rounds": [
				{
					"enemies": {
						"egui": 1,
						"tianxieguichi": 3,
						"shouwu": 1
					}
				}
			],
			"money": 0,
			"exp": 0
		},
		{
			"name": "第十三章 唐纸伞妖1",
			"sushi": 3,
			"rounds": [
				{
					"enemies": {
						"tangzhisanyao": 1,
						"tianxieguilv": 2
					}
				}
			],
			"money": 0,
			"exp": 0
		},
		{
			"name": "第十三章 唐纸伞妖2",
			"sushi": 3,
			"rounds": [
				{
					"enemies": {
						"tangzhisanyao": 1,
						"tianxieguilv": 2
					}
				}
			],
			"money": 0,
			"exp": 0
		},
		{
			"name": "第十三章 唐纸伞妖3",
			"sushi": 3,
			"rounds": [
				{
					"enemies": {
						"tangzhisanyao": 1,
						"tianxieguilv": 2,
						"shouwu": 1
					}
				}
			],
			"money": 0,
			"exp": 0
		},
		{
			"name": "第十三章 首领：首无",
			"sushi": 3,
			"rounds": [
				{
					"enemies": {
						"shouwu": 1,
						"gunv": 1,
						"denglonggui": 1
					}
				}
			],
			"money": 0,
			"exp": 0
		},
		{
			"name": "第十四章 帚神1",
			"sushi": 3,
			"rounds": [
				{
					"enemies": {
						"zhoushen": 1,
						"tianxieguichi": 3
					}
				}
			],
			"money": 0,
			"exp": 0
		},
		{
			"name": "第十四章 帚神2",
			"sushi": 3,
			"rounds": [
				{
					"enemies": {
						"zhoushen": 1,
						"tianxieguichi": 3
					}
				}
			],
			"money": 0,
			"exp": 0
		},
		{
			"name": "第十四章 帚神3",
			"sushi": 3,
			"rounds": [
				{
					"enemies": {
						"zhoushen": 1,
						"tianxieguichi": 3
					}
				}
			],
			"money": 0,
			"exp": 0
		},
		{
			"name": "第十四章 涂壁1",
			"sushi": 3,
			"rounds": [
				{
					"enemies": {
						"tubi": 6
					}
				}
			],
			"money": 0,
			"exp": 0
		},
		{
			"name": "第十四章 涂壁2",
			"sushi": 3,
			"rounds": [
				{
					"enemies": {
						"tubi": 6
					}
				}
			],
			"money": 0,
			"exp": 0
		},
		{
			"name": "第十四章 涂壁3",
			"sushi": 3,
			"rounds": [
				{
					"enemies": {
						"tubi": 6
					}
				},
				{
					"enemies": {
						"shimengmo": 1
					}
				}
			],
			"money": 0,
			"exp": 0
		},
		{
			"name": "第十四章 首领：食梦貘",
			"sushi": 3,
			"rounds": [
				{
					"enemies": {
						"shimengmo": 1,
						"tianxieguichi": 3
					}
				},
				{
					"enemies": {
						"shimengmo": 4
					}
				}
			],
			"money": 0,
			"exp": 0
		},
		{
			"name": "第十五章 天邪鬼绿1",
			"sushi": 3,
			"rounds": [
				{
					"enemies": {
						"tianxieguilv": 1,
						"chishe": 1,
						"tianxieguichi": 2
					}
				}
			],
			"money": 0,
			"exp": 0
		},
		{
			"name": "第十五章 天邪鬼绿2",
			"sushi": 3,
			"rounds": [
				{
					"enemies": {
						"tianxieguilv": 1,
						"chishe": 1,
						"tianxieguichi": 2
					}
				}
			],
			"money": 0,
			"exp": 0
		},
		{
			"name": "第十五章 天邪鬼绿3",
			"sushi": 3,
			"rounds": [
				{
					"enemies": {
						"tianxieguilv": 1,
						"chishe": 1,
						"tianxieguichi": 2
					}
				}
			],
			"money": 0,
			"exp": 0
		},
		{
			"name": "第十五章 提灯小僧1",
			"sushi": 3,
			"rounds": [
				{
					"enemies": {
						"tidengxiaoseng": 1,
						"chishe": 1,
						"jiumingmao": 2
					}
				}
			],
			"money": 0,
			"exp": 0
		},
		{
			"name": "第十五章 提灯小僧2",
			"sushi": 3,
			"rounds": [
				{
					"enemies": {
						"tidengxiaoseng": 1,
						"chishe": 1,
						"jiumingmao": 2
					}
				}
			],
			"money": 0,
			"exp": 0
		},
		{
			"name": "第十五章 提灯小僧3",
			"sushi": 3,
			"rounds": [
				{
					"enemies": {
						"tidengxiaoseng": 1,
						"chishe": 1,
						"jiumingmao": 2
					}
				},
				{
					"enemies": {
						"datiangou": 1
					}
				}
			],
			"money": 0,
			"exp": 0
		},
		{
			"name": "第十五章 首领：跳跳妹妹",
			"sushi": 3,
			"rounds": [
				{
					"enemies": {
						"tiaotiaomeimei": 1,
						"jiumingmao": 3
					}
				}
			],
			"money": 0,
			"exp": 0
		},
		{
			"name": "第十六章 饿鬼1",
			"sushi": 3,
			"rounds": [
				{
					"enemies": {
						"egui": 1,
						"shantu": 1,
						"shantong": 2
					}
				}
			],
			"money": 0,
			"exp": 0
		},
		{
			"name": "第十六章 饿鬼2",
			"sushi": 3,
			"rounds": [
				{
					"enemies": {
						"egui": 1,
						"shantu": 1,
						"shantong": 2
					}
				}
			],
			"money": 0,
			"exp": 0
		},
		{
			"name": "第十六章 饿鬼3",
			"sushi": 3,
			"rounds": [
				{
					"enemies": {
						"egui": 1,
						"shantu": 1,
						"shantong": 2
					}
				}
			],
			"money": 0,
			"exp": 0
		},
		{
			"name": "第十六章 赤舌1",
			"sushi": 3,
			"rounds": [
				{
					"enemies": {
						"chishe": 1,
						"jishenghun": 3
					}
				}
			],
			"money": 0,
			"exp": 0
		},
		{
			"name": "第十六章 赤舌2",
			"sushi": 3,
			"rounds": [
				{
					"enemies": {
						"chishe": 1,
						"jishenghun": 3
					}
				},
				{
					"enemies": {
						"chishe": 1
					}
				}
			],
			"money": 0,
			"exp": 0
		},
		{
			"name": "第十六章 赤舌3",
			"sushi": 3,
			"rounds": [
				{
					"enemies": {
						"chishe": 1,
						"jishenghun": 3
					}
				}
			],
			"money": 0,
			"exp": 0
		},
		{
			"name": "第十六章 首领：判官",
			"sushi": 3,
			"rounds": [
				{
					"enemies": {
						"panguan": 1,
						"guishihei": 1,
						"guishibai": 1
					}
				}
			],
			"money": 0,
			"exp": 0
		},
		{
			"name": "第十七章 鸦天狗1",
			"sushi": 3,
			"rounds": [
				{
					"enemies": {
						"yatiangou": 1,
						"fengxiaoqilin": 3
					}
				}
			],
			"money": 0,
			"exp": 0
		},
		{
			"name": "第十七章 鸦天狗2",
			"sushi": 3,
			"rounds": [
				{
					"enemies": {
						"yatiangou": 1,
						"fengxiaoqilin": 3
					}
				}
			],
			"money": 0,
			"exp": 0
		},
		{
			"name": "第十七章 鸦天狗3",
			"sushi": 3,
			"rounds": [
				{
					"enemies": {
						"yatiangou": 1,
						"fengxiaoqilin": 3
					}
				}
			],
			"money": 0,
			"exp": 0
		},
		{
			"name": "第十七章 狸猫1",
			"sushi": 3,
			"rounds": [
				{
					"enemies": {
						"limao": 1,
						"huoxiaoqilin": 3
					}
				}
			],
			"money": 0,
			"exp": 0
		},
		{
			"name": "第十七章 狸猫2",
			"sushi": 3,
			"rounds": [
				{
					"enemies": {
						"limao": 1,
						"huoxiaoqilin": 3
					}
				}
			],
			"money": 0,
			"exp": 0
		},
		{
			"name": "第十七章 狸猫3",
			"sushi": 3,
			"rounds": [
				{
					"enemies": {
						"limao": 1,
						"huoxiaoqilin": 3,
						"heifenghuang": 1
					}
				}
			],
			"money": 0,
			"exp": 0
		},
		{
			"name": "第十七章 首领：荒川之主",
			"sushi": 3,
			"rounds": [
				{
					"enemies": {
						"huangchuanzhizhu": 1,
						"denglonggui": 1,
						"gunv": 1
					}
				}
			],
			"money": 0,
			"exp": 0
		},
		{
			"name": "第十八章 九命猫1",
			"sushi": 3,
			"rounds": [
				{
					"enemies": {
						"jiumingmao": 6
					}
				}
			],
			"money": 0,
			"exp": 0
		},
		{
			"name": "第十八章 九命猫2",
			"sushi": 3,
			"rounds": [
				{
					"enemies": {
						"jiumingmao": 6
					}
				}
			],
			"money": 0,
			"exp": 0
		},
		{
			"name": "第十八章 九命猫3",
			"sushi": 3,
			"rounds": [
				{
					"enemies": {
						"jiumingmao": 6
					}
				}
			],
			"money": 0,
			"exp": 0
		},
		{
			"name": "第十八章 三尾狐1",
			"sushi": 3,
			"rounds": [
				{
					"enemies": {
						"sanweihu": 2,
						"jiumingmao": 2
					}
				},
				{
					"enemies": {
						"datiangou": 1
					}
				}
			],
			"money": 0,
			"exp": 0
		},
		{
			"name": "第十八章 三尾狐2",
			"sushi": 3,
			"rounds": [
				{
					"enemies": {
						"sanweihu": 2,
						"jiumingmao": 2
					}
				}
			],
			"money": 0,
			"exp": 0
		},
		{
			"name": "第十八章 三尾狐3",
			"sushi": 3,
			"rounds": [
				{
					"enemies": {
						"sanweihu": 2,
						"jiumingmao": 2
					}
				}
			],
			"money": 0,
			"exp": 0
		},
		{
			"name": "第十八章 首领：大天狗",
			"sushi": 3,
			"rounds": [
				{
					"enemies": {
						"datiangou": 1,
						"yatiangou": 3
					}
				}
			],
			"money": 0,
			"exp": 0
		},
		{
			"name": "红叶的羁绊 第一层",
			"sushi": 3,
			"rounds": [
				{
					"enemies": {
						"guanhu": 4,
						"egui": 4,
						"guinvhongye": 1,
						"jue": 3
					}
				}
			],
			"money": 0,
			"exp": 0
		},
		{
			"name": "红叶的羁绊 第一层2回合",
			"sushi": 3,
			"rounds": [
				{
					"enemies": {
						"egui": 4,
						"guinvhongye": 1,
						"jue": 3,
						"guanhu": 4
					}
				}
			],
			"money": 0,
			"exp": 0
		},
		{
			"name": "红叶的羁绊 第一层3回合",
			"sushi": 3,
			"rounds": [
				{
					"enemies": {
						"guinvhongye": 1,
						"jue": 3,
						"guanhu": 4,
						"egui": 4
					}
				}
			],
			"money": 0,
			"exp": 0
		},
		{
			"name": "红叶的羁绊 第二层",
			"sushi": 3,
			"rounds": [
				{
					"enemies": {
						"guanhu": 4,
						"egui": 4,
						"guinvhongye": 1,
						"tiaotiaodidi": 1,
						"tiaotiaogege": 1,
						"tiaotiaomeimei": 1
					}
				}
			],
			"money": 0,
			"exp": 0
		},
		{
			"name": "红叶的羁绊 第二层2回合",
			"sushi": 3,
			"rounds": [
				{
					"enemies": {
						"egui": 4,
						"guinvhongye": 1,
						"tiaotiaodidi": 1,
						"tiaotiaogege": 1,
						"tiaotiaomeimei": 1,
						"guanhu": 4
					}
				}
			],
			"money": 0,
			"exp": 0
		},
		{
			"name": "红叶的羁绊 第二层3回合",
			"sushi": 3,
			"rounds": [
				{
					"enemies": {
						"guinvhongye": 1,
						"tiaotiaodidi": 1,
						"tiaotiaogege": 1,
						"tiaotiaomeimei": 1,
						"guanhu": 4,
						"egui": 4
					}
				}
			],
			"money": 0,
			"exp": 0
		},
		{
			"name": "红叶的羁绊 第三层",
			"sushi": 3,
			"rounds": [
				{
					"enemies": {
						"guanhu": 4,
						"egui": 4,
						"guinvhongye": 1,
						"shouwu": 2,
						"sanweihu": 1
					}
				}
			],
			"money": 0,
			"exp": 0
		},
		{
			"name": "红叶的羁绊 第三层2回合",
			"sushi": 3,
			"rounds": [
				{
					"enemies": {
						"egui": 4,
						"guinvhongye": 1,
						"shouwu": 2,
						"sanweihu": 1,
						"guanhu": 3,
						"tianxieguihuang": 1
					}
				}
			],
			"money": 0,
			"exp": 0
		},
		{
			"name": "红叶的羁绊 第三层3回合",
			"sushi": 3,
			"rounds": [
				{
					"enemies": {
						"guinvhongye": 1,
						"shouwu": 2,
						"sanweihu": 1,
						"guanhu": 3,
						"tianxieguihuang": 1,
						"egui": 3,
						"bingyong": 1
					}
				}
			],
			"money": 0,
			"exp": 0
		},
		{
			"name": "红叶的羁绊 第四层",
			"sushi": 3,
			"rounds": [
				{
					"enemies": {
						"guanhu": 3,
						"tianxieguihuang": 1,
						"egui": 3,
						"bingyong": 1,
						"guinvhongye": 1,
						"choushizhinv": 1,
						"yatiangou": 2
					}
				}
			],
			"money": 0,
			"exp": 0
		},
		{
			"name": "妖刀之秘籍 第一层",
			"sushi": 3,
			"rounds": [
				{
					"enemies": {
						"tianxieguiqing": 4,
						"limao": 4,
						"yaodaoji": 1,
						"daomuxiaogui": 3
					}
				}
			],
			"money": 0,
			"exp": 0
		},
		{
			"name": "妖刀之秘籍 第一层2回合",
			"sushi": 3,
			"rounds": [
				{
					"enemies": {
						"limao": 4,
						"yaodaoji": 1,
						"daomuxiaogui": 3,
						"tianxieguiqing": 4
					}
				}
			],
			"money": 0,
			"exp": 0
		},
		{
			"name": "妖刀之秘籍 第一层3回合",
			"sushi": 3,
			"rounds": [
				{
					"enemies": {
						"yaodaoji": 1,
						"daomuxiaogui": 3,
						"tianxieguiqing": 4,
						"limao": 4
					}
				}
			],
			"money": 0,
			"exp": 0
		},
		{
			"name": "妖刀之秘籍 第二层",
			"sushi": 3,
			"rounds": [
				{
					"enemies": {
						"tianxieguiqing": 4,
						"limao": 4,
						"yaodaoji": 1,
						"hudiejing": 3
					}
				}
			],
			"money": 0,
			"exp": 0
		},
		{
			"name": "妖刀之秘籍 第二层2回合",
			"sushi": 3,
			"rounds": [
				{
					"enemies": {
						"limao": 4,
						"yaodaoji": 1,
						"hudiejing": 3,
						"tianxieguiqing": 4
					}
				}
			],
			"money": 0,
			"exp": 0
		},
		{
			"name": "妖刀之秘籍 第二层3回合",
			"sushi": 3,
			"rounds": [
				{
					"enemies": {
						"yaodaoji": 1,
						"hudiejing": 3,
						"tianxieguiqing": 4,
						"limao": 4
					}
				}
			],
			"money": 0,
			"exp": 0
		},
		{
			"name": "妖刀之秘籍 第三层",
			"sushi": 3,
			"rounds": [
				{
					"enemies": {
						"tianxieguiqing": 4,
						"limao": 4,
						"yaodaoji": 1,
						"yunv": 3
					}
				}
			],
			"money": 0,
			"exp": 0
		},
		{
			"name": "妖刀之秘籍 第三层2回合",
			"sushi": 3,
			"rounds": [
				{
					"enemies": {
						"limao": 4,
						"yaodaoji": 1,
						"yunv": 3,
						"tianxieguiqing": 3,
						"tubi": 1
					}
				}
			],
			"money": 0,
			"exp": 0
		},
		{
			"name": "妖刀之秘籍 第三层3回合",
			"sushi": 3,
			"rounds": [
				{
					"enemies": {
						"yaodaoji": 1,
						"yunv": 3,
						"tianxieguiqing": 3,
						"tubi": 1,
						"limao": 3,
						"hudiejing": 1
					}
				}
			],
			"money": 0,
			"exp": 0
		},
		{
			"name": "妖刀之秘籍 第四层",
			"sushi": 3,
			"rounds": [
				{
					"enemies": {
						"tianxieguiqing": 3,
						"tubi": 1,
						"limao": 3,
						"hudiejing": 1,
						"yaodaoji": 1,
						"sanweihu": 3
					}
				}
			],
			"money": 0,
			"exp": 0
		},
		{
			"name": "河畔童谣 第一层",
			"sushi": 3,
			"rounds": [
				{
					"enemies": {
						"daomuxiaogui": 1,
						"tidengxiaoseng": 3,
						"tongnv": 1,
						"tongnan": 3,
						"hetong": 1,
						"fengweidamo": 1,
						"yuhangdamo": 1,
						"zhaofudamo": 1,
						"dajidamo": 1
					}
				}
			],
			"money": 0,
			"exp": 0
		},
		{
			"name": "河畔童谣 第一层2回合",
			"sushi": 3,
			"rounds": [
				{
					"enemies": {
						"tongnv": 1,
						"tongnan": 3,
						"hetong": 1,
						"fengweidamo": 1,
						"yuhangdamo": 1,
						"zhaofudamo": 1,
						"dajidamo": 1,
						"daomuxiaogui": 1,
						"tidengxiaoseng": 3
					}
				}
			],
			"money": 0,
			"exp": 0
		},
		{
			"name": "河畔童谣 第一层3回合",
			"sushi": 3,
			"rounds": [
				{
					"enemies": {
						"hetong": 1,
						"fengweidamo": 1,
						"yuhangdamo": 1,
						"zhaofudamo": 1,
						"dajidamo": 1,
						"daomuxiaogui": 1,
						"tidengxiaoseng": 3,
						"duyanxiaoseng": 1,
						"shantong": 3
					}
				}
			],
			"money": 0,
			"exp": 0
		},
		{
			"name": "河畔童谣 第二层",
			"sushi": 3,
			"rounds": [
				{
					"enemies": {
						"daomuxiaogui": 1,
						"tidengxiaoseng": 3,
						"duyanxiaoseng": 1,
						"shantong": 3,
						"hetong": 1,
						"baitongzi": 1,
						"zuofutongzi": 1,
						"heitongzi": 1
					}
				}
			],
			"money": 0,
			"exp": 0
		},
		{
			"name": "河畔童谣 第二层2回合",
			"sushi": 3,
			"rounds": [
				{
					"enemies": {
						"duyanxiaoseng": 1,
						"shantong": 3,
						"hetong": 1,
						"baitongzi": 1,
						"zuofutongzi": 1,
						"heitongzi": 1,
						"huibishou": 1,
						"wushizhiling": 3
					}
				}
			],
			"money": 0,
			"exp": 0
		},
		{
			"name": "河畔童谣 第二层3回合",
			"sushi": 3,
			"rounds": [
				{
					"enemies": {
						"hetong": 1,
						"baitongzi": 1,
						"zuofutongzi": 1,
						"heitongzi": 1,
						"huibishou": 1,
						"wushizhiling": 3,
						"yanyanluo": 1,
						"shifagui": 3
					}
				}
			],
			"money": 0,
			"exp": 0
		},
		{
			"name": "河畔童谣 第三层",
			"sushi": 3,
			"rounds": [
				{
					"enemies": {
						"huibishou": 1,
						"wushizhiling": 3,
						"yanyanluo": 1,
						"shifagui": 3,
						"hetong": 1,
						"denglonggui": 2,
						"chishe": 1
					}
				}
			],
			"money": 0,
			"exp": 0
		},
		{
			"name": "河畔童谣 第三层2回合",
			"sushi": 3,
			"rounds": [
				{
					"enemies": {
						"yanyanluo": 1,
						"shifagui": 3,
						"hetong": 1,
						"denglonggui": 2,
						"chishe": 1,
						"lianyou": 1,
						"heibao": 3
					}
				}
			],
			"money": 0,
			"exp": 0
		},
		{
			"name": "河畔童谣 第三层3回合",
			"sushi": 3,
			"rounds": [
				{
					"enemies": {
						"hetong": 1,
						"denglonggui": 2,
						"chishe": 1,
						"lianyou": 1,
						"heibao": 3,
						"yingcao": 1,
						"jue": 3
					}
				}
			],
			"money": 0,
			"exp": 0
		},
		{
			"name": "河畔童谣 第四层",
			"sushi": 3,
			"rounds": [
				{
					"enemies": {
						"lianyou": 1,
						"heibao": 3,
						"yingcao": 1,
						"jue": 3,
						"hetong": 1,
						"choushizhinv": 2,
						"bingyong": 1
					}
				}
			],
			"money": 0,
			"exp": 0
		},
		{
			"name": "雨女的等候 第一层",
			"sushi": 3,
			"rounds": [
				{
					"enemies": {
						"daomuxiaogui": 3,
						"tangzhisanyao": 1,
						"jiumingmao": 3,
						"tieshu": 1,
						"zuofutongzi": 3,
						"yunv": 1
					}
				}
			],
			"money": 0,
			"exp": 0
		},
		{
			"name": "雨女的等候 第一层2回合",
			"sushi": 3,
			"rounds": [
				{
					"enemies": {
						"jiumingmao": 3,
						"tieshu": 1,
						"zuofutongzi": 3,
						"yunv": 1,
						"daomuxiaogui": 3,
						"tangzhisanyao": 1
					}
				}
			],
			"money": 0,
			"exp": 0
		},
		{
			"name": "雨女的等候 第一层3回合",
			"sushi": 3,
			"rounds": [
				{
					"enemies": {
						"zuofutongzi": 3,
						"yunv": 1,
						"daomuxiaogui": 3,
						"tangzhisanyao": 1,
						"jiumingmao": 3,
						"tieshu": 1
					}
				}
			],
			"money": 0,
			"exp": 0
		},
		{
			"name": "雨女的等候 第二层",
			"sushi": 3,
			"rounds": [
				{
					"enemies": {
						"daomuxiaogui": 3,
						"tangzhisanyao": 1,
						"jiumingmao": 3,
						"tieshu": 1,
						"shouwu": 3,
						"yunv": 1
					}
				}
			],
			"money": 0,
			"exp": 0
		},
		{
			"name": "雨女的等候 第二层2回合",
			"sushi": 3,
			"rounds": [
				{
					"enemies": {
						"jiumingmao": 3,
						"tieshu": 1,
						"shouwu": 3,
						"yunv": 1,
						"daomuxiaogui": 3,
						"tangzhisanyao": 1
					}
				}
			],
			"money": 0,
			"exp": 0
		},
		{
			"name": "雨女的等候 第二层3回合",
			"sushi": 3,
			"rounds": [
				{
					"enemies": {
						"shouwu": 3,
						"yunv": 1,
						"daomuxiaogui": 3,
						"tangzhisanyao": 1,
						"jiumingmao": 3,
						"tieshu": 1
					}
				}
			],
			"money": 0,
			"exp": 0
		},
		{
			"name": "雨女的等候 第三层",
			"sushi": 3,
			"rounds": [
				{
					"enemies": {
						"daomuxiaogui": 3,
						"tangzhisanyao": 1,
						"jiumingmao": 3,
						"tieshu": 1,
						"wushizhiling": 3,
						"yunv": 1
					}
				}
			],
			"money": 0,
			"exp": 0
		},
		{
			"name": "雨女的等候 第三层2回合",
			"sushi": 3,
			"rounds": [
				{
					"enemies": {
						"jiumingmao": 3,
						"tieshu": 1,
						"wushizhiling": 3,
						"yunv": 1,
						"tangzhisanyao": 3,
						"chishe": 1
					}
				}
			],
			"money": 0,
			"exp": 0
		},
		{
			"name": "雨女的等候 第三层3回合",
			"sushi": 3,
			"rounds": [
				{
					"enemies": {
						"wushizhiling": 3,
						"yunv": 1,
						"tangzhisanyao": 3,
						"chishe": 1,
						"jue": 3,
						"choushizhinv": 1
					}
				}
			],
			"money": 0,
			"exp": 0
		},
		{
			"name": "雨女的等候 第四层",
			"sushi": 3,
			"rounds": [
				{
					"enemies": {
						"tangzhisanyao": 3,
						"chishe": 1,
						"jue": 3,
						"choushizhinv": 1,
						"gunv": 4,
						"yunv": 1
					}
				}
			],
			"money": 0,
			"exp": 0
		},
		{
			"name": "御魂副本 第一层",
			"sushi": 4,
			"rounds": [
				{
					"enemies": {
						"sanweihu": 1,
						"tianxieguihuang": 1,
						"tianxieguiqing": 1,
						"shantong": 1,
						"tubi": 1,
						"duyanxiaoseng": 1,
						"baqidashe": 1,
						"tianxieguichi": 2
					}
				}
			],
			"money": 0,
			"exp": 0
		},
		{
			"name": "御魂副本 第二层",
			"sushi": 4,
			"rounds": [
				{
					"enemies": {
						"yaohu": 1,
						"liyujing": 1,
						"hetong": 1,
						"xixieji": 1,
						"yingcao": 1,
						"bingyong": 1,
						"baqidashe": 1,
						"tongnv": 2
					}
				}
			],
			"money": 0,
			"exp": 0
		},
		{
			"name": "御魂副本 第三层",
			"sushi": 4,
			"rounds": [
				{
					"enemies": {
						"taohuayao": 1,
						"hudiejing": 1,
						"qingwaciqi": 1,
						"haifangzhu": 1,
						"liyujing": 1,
						"jiaotu": 1,
						"baqidashe": 1,
						"zuofutongzi": 2
					}
				}
			],
			"money": 0,
			"exp": 0
		},
		{
			"name": "御魂副本 第四层",
			"sushi": 4,
			"rounds": [
				{
					"enemies": {
						"quanshen": 1,
						"tongnan": 1,
						"tongnv": 1,
						"datiangou": 1,
						"guishihei": 1,
						"guishibai": 1,
						"baqidashe": 1,
						"shimengmo": 2
					}
				}
			],
			"money": 0,
			"exp": 0
		},
		{
			"name": "御魂副本 第五层",
			"sushi": 4,
			"rounds": [
				{
					"enemies": {
						"lianyou": 1,
						"gunv": 1,
						"choushizhinv": 1,
						"kuileishi": 1,
						"tiaotiaogege": 1,
						"duyanxiaoseng": 1,
						"baqidashe": 1,
						"mengpo": 2
					}
				}
			],
			"money": 0,
			"exp": 0
		},
		{
			"name": "御魂副本 第六层",
			"sushi": 4,
			"rounds": [
				{
					"enemies": {
						"yunv": 1,
						"mengpo": 1,
						"zuofutongzi": 1,
						"yanmo": 1,
						"wugushi": 1,
						"yatiangou": 1,
						"baqidashe": 1,
						"gunv": 2
					}
				}
			],
			"money": 0,
			"exp": 0
		},
		{
			"name": "御魂副本 第七层",
			"sushi": 4,
			"rounds": [
				{
					"enemies": {
						"choushizhinv": 1,
						"fenghuanghuo": 1,
						"shifagui": 1,
						"shantu": 1,
						"jiutuntongzi": 1,
						"yaoqinshi": 1,
						"baqidashe": 1,
						"huangchuanzhizhu": 2
					}
				}
			],
			"money": 0,
			"exp": 0
		},
		{
			"name": "御魂副本 第八层",
			"sushi": 4,
			"rounds": [
				{
					"enemies": {
						"guanhu": 1,
						"panguan": 1,
						"egui": 1,
						"hudiejing": 1,
						"bailang": 1,
						"jiaotu": 1,
						"baqidashe": 1,
						"cimutongzi": 2
					}
				}
			],
			"money": 0,
			"exp": 0
		},
		{
			"name": "御魂副本 第九层",
			"sushi": 4,
			"rounds": [
				{
					"enemies": {
						"jiaotu": 1,
						"yingcao": 1,
						"liyujing": 1,
						"limao": 1,
						"qingji": 1,
						"shimengmo": 1,
						"baqidashe": 1,
						"liangmianfo": 2
					}
				}
			],
			"money": 0,
			"exp": 0
		},
		{
			"name": "御魂副本 第十层",
			"sushi": 4,
			"rounds": [
				{
					"enemies": {
						"erkounv": 1,
						"jue": 1,
						"yingcao": 1,
						"jiaotu": 1,
						"qinghangdeng": 1,
						"jiutuntongzi": 1,
						"baqidashe": 1,
						"datiangou": 2
					}
				}
			],
			"money": 0,
			"exp": 0
		},
		{
			"name": "妖气封印 跳跳哥哥",
			"sushi": 4,
			"rounds": [
				{
					"enemies": {
						"tianxieguilv": 4,
						"zhoushen": 2,
						"tianxieguiqing": 3,
						"tianxieguichi": 1,
						"tiaotiaogege": 3,
						"tianxieguihuang": 1
					}
				}
			],
			"money": 0,
			"exp": 0
		},
		{
			"name": "妖气封印 椒图",
			"sushi": 4,
			"rounds": [
				{
					"enemies": {
						"tianxieguilv": 8,
						"tianxieguihuang": 2,
						"tianxieguichi": 1,
						"jiaotu": 3
					}
				}
			],
			"money": 0,
			"exp": 0
		},
		{
			"name": "妖气封印 骨女",
			"sushi": 4,
			"rounds": [
				{
					"enemies": {
						"zhoushen": 4,
						"tianxieguichi": 1,
						"tianxieguilv": 6,
						"gunv": 3
					}
				}
			],
			"money": 0,
			"exp": 0
		},
		{
			"name": "妖气封印 饿鬼",
			"sushi": 4,
			"rounds": [
				{
					"enemies": {
						"tubi": 1,
						"tianxieguilv": 6,
						"tangzhisanyao": 1,
						"egui": 3,
						"tidengxiaoseng": 3
					}
				}
			],
			"money": 0,
			"exp": 0
		},
		{
			"name": "妖气封印 二口女",
			"sushi": 4,
			"rounds": [
				{
					"enemies": {
						"zhoushen": 4,
						"tianxieguiqing": 3,
						"tidengxiaoseng": 4,
						"erkounv": 1
					}
				}
			],
			"money": 0,
			"exp": 0
		},
		{
			"name": "妖气封印 海坊主",
			"sushi": 4,
			"rounds": [
				{
					"enemies": {
						"tidengxiaoseng": 4,
						"tianxieguihuang": 3,
						"tianxieguiqing": 1,
						"tianxieguilv": 1,
						"tianxieguichi": 2,
						"haifangzhu": 3
					}
				}
			],
			"money": 0,
			"exp": 0
		},
		{
			"name": "妖气封印 鬼使黑",
			"sushi": 4,
			"rounds": [
				{
					"enemies": {
						"tianxieguichi": 1,
						"tubi": 4,
						"zhoushen": 3,
						"guishihei": 3,
						"tidengxiaoseng": 3
					}
				}
			],
			"money": 0,
			"exp": 0
		},
		{
			"name": "妖气封印 金币妖怪",
			"sushi": 4,
			"rounds": [
				{
					"enemies": {
						"tieshu": 18
					}
				}
			],
			"money": 0,
			"exp": 0
		},
		{
			"name": "妖气封印 经验妖怪",
			"sushi": 4,
			"rounds": [
				{
					"enemies": {
						"fengweidamo": 16
					}
				}
			],
			"money": 0,
			"exp": 0
		}
	]
}